rdotherout/__init__.py
rdotherout/mainModel.py
rdotherout/metadata.py
rdotherout/operation.py
rdotherout/utility.py
rdotherout-1.1.8.dist-info/METADATA
rdotherout-1.1.8.dist-info/WHEEL
rdotherout-1.1.8.dist-info/top_level.txt
rdotherout-1.1.8.dist-info/RECORD
